cisco_discovery/Adjacency.py
cisco_discovery/ConnectHandler.py
cisco_discovery/ConnectHandler_async.py
cisco_discovery/Device_Role.py
cisco_discovery/Discovery.py
cisco_discovery/Draw_io.py
cisco_discovery/File_Save.py
cisco_discovery/__init__.py
cisco_discovery-1.1.dist-info/LICENSE
cisco_discovery-1.1.dist-info/METADATA
cisco_discovery-1.1.dist-info/WHEEL
cisco_discovery-1.1.dist-info/top_level.txt
cisco_discovery-1.1.dist-info/RECORD
