Metadata-Version: 2.2
Name: cisco_discovery
Version: 1.1
License-File: LICENSE
Requires-Dist: pandas>=2.2.3
Requires-Dist: openpyxl>=3.1.5
Requires-Dist: genie>=25.3
Requires-Dist: pyats>=25.3
Requires-Dist: netmiko>=4.5.0
Requires-Dist: dotenv>=0.9.9
Dynamic: description
Dynamic: description-content-type
Dynamic: requires-dist
